{"year_range_month":{"snow_mean":[2.3,35.2],"snow_median":[1.8,32.4],"temp_mean":[23.1,38.1],"avg_anomaly":[-18.3,17.9],"median_anomaly":[-15.9,15.1]},"state_year_month_range":{"snow_mean":[0.1,44.8],"snow_median":[0.1,43.2],"temp_mean":[14.5,62.5],"avg_anomaly":[-50.2,23.5],"median_anomaly":[-55.2,27.5]},"el_year_month_range":{"snow_mean":[0.1,43.9],"snow_median":[0.1,40],"temp_mean":[14.2,57.4],"avg_anomaly":[-34.9,26.8],"median_anomaly":[-38,30.3]},"stae_el_year_range":{"snow_mean":[0.2,40.9],"snow_median":[0.2,42.3],"temp_mean":[22.3,41.2],"avg_anomaly":[-38,19],"median_anomaly":[-38,17.1]},"state_el_year_month_range":{"snow_mean":[0.1,59.8],"snow_median":[0.1,60],"temp_mean":[11.5,68],"avg_anomaly":[-67.9,27.9],"median_anomaly":[-67.9,41.6]}}